mongo_sio/__init__.py
test/__init__.py
test/test_wire.py
mongo_sio-0.0.1.dist-info/LICENSE
mongo_sio-0.0.1.dist-info/METADATA
mongo_sio-0.0.1.dist-info/WHEEL
mongo_sio-0.0.1.dist-info/top_level.txt
mongo_sio-0.0.1.dist-info/RECORD
